MANIFEST.in
README.md
setup.py
sentry_groveio/__init__.py
sentry_groveio/models.py
sentry_groveio.egg-info/PKG-INFO
sentry_groveio.egg-info/SOURCES.txt
sentry_groveio.egg-info/dependency_links.txt
sentry_groveio.egg-info/entry_points.txt
sentry_groveio.egg-info/not-zip-safe
sentry_groveio.egg-info/requires.txt
sentry_groveio.egg-info/top_level.txt