Metadata-Version: 1.0
Name: sentry-groveio
Version: 0.2.0
Summary: A Sentry extension which integrates with Grove.io.
Home-page: http://github.com/mattrobenolt/sentry-groveio
Author: Matt Robenolt
Author-email: matt@ydekproductons.com
License: BSD
Platform: UNKNOWN
Classifier: Framework :: Django
Classifier: Intended Audience :: Developers
Classifier: Intended Audience :: System Administrators
Classifier: Operating System :: OS Independent
Classifier: Topic :: Software Development
